pptxlib/__init__.py
pptxlib/app.py
pptxlib/base.py
pptxlib/client.py
pptxlib/color.py
pptxlib/compat.py
pptxlib/contrib/__init__.py
pptxlib/contrib/gantt.py
pptxlib/font.py
pptxlib/presentation.py
pptxlib/py.typed
pptxlib/shape.py
pptxlib/slide.py
pptxlib/table.py
pptxlib-0.2.8.dist-info/WHEEL
pptxlib-0.2.8.dist-info/METADATA
pptxlib-0.2.8.dist-info/RECORD
