Metadata-Version: 2.3
Name: pptxlib
Version: 0.2.8
Summary: Automate Microsoft PowerPoint operations. Create, modify, and manage PowerPoint presentations programmatically with a simple and intuitive interface
Keywords: automation,com,microsoft,office,powerpoint,pptx,presentation,win32com,windows
Author: daizutabi
Author-email: daizutabi <daizutabi@gmail.com>
License: MIT License
Classifier: Development Status :: 4 - Beta
Classifier: Intended Audience :: Developers
Classifier: License :: OSI Approved :: MIT License
Classifier: Operating System :: Microsoft :: Windows
Classifier: Programming Language :: Python
Classifier: Programming Language :: Python :: 3.11
Classifier: Programming Language :: Python :: 3.12
Classifier: Programming Language :: Python :: 3.13
Classifier: Programming Language :: Python :: 3.14
Classifier: Topic :: Office/Business
Classifier: Typing :: Typed
Requires-Dist: pywin32
Requires-Dist: python-dateutil>=2.8.2
Requires-Python: >=3.11
Project-URL: Documentation, https://github.com/daizutabi/pptxlib
Project-URL: Issues, https://github.com/daizutabi/pptxlib/issues
Project-URL: Source, https://github.com/daizutabi/pptxlib
